honeybee_energy_ref/__init__.py
honeybee_energy_ref/_extend_honeybee_energy_ref.py
honeybee_energy_ref/document_ref.py
honeybee_energy_ref/image_ref.py
honeybee_energy_ref/properties/__init__.py
honeybee_energy_ref/properties/hb_obj.py
honeybee_ref-0.2.1.dist-info/licenses/LICENSE
honeybee_ref-0.2.1.dist-info/METADATA
honeybee_ref-0.2.1.dist-info/WHEEL
honeybee_ref-0.2.1.dist-info/top_level.txt
honeybee_ref-0.2.1.dist-info/RECORD
