Metadata-Version: 2.4
Name: honeybee-ref
Version: 0.2.1
Summary: A Honeybee extension for tracking reference information and sources..
Author-email: Ed May <phtools@bldgtyp.com>
Maintainer-email: Ed May <phtools@bldgtyp.com>
License-Expression: GPL-3.0-or-later
Project-URL: homepage, https://www.passivehousetools.com/
Project-URL: repository, https://github.com/PH-Tools/honeybee_ref
Keywords: Honeybee,Honeybee-Energy,Passive House,Building Retrofit,Architecture,Energy Modeling
Classifier: Programming Language :: Python :: 2.7
Classifier: Operating System :: OS Independent
Requires-Python: >=2.7
License-File: LICENSE
Requires-Dist: honeybee-energy>=1.116.32
Provides-Extra: dev
Requires-Dist: black; extra == "dev"
Requires-Dist: isort; extra == "dev"
Requires-Dist: pytest; extra == "dev"
Requires-Dist: pytest-cov; extra == "dev"
Dynamic: license-file
